{
  "schema_version": "2.1",
  "model": "A4",
  "market": "UK",
  "drive_side": "RHD",
  "generations": [
    {
      "id": "b5",
      "name": "A4 B5",
      "years": "1995-2001",
      "platform": "Audi longitudinal architecture; exact platform revision requires generation evidence",
      "immobiliser_family": "Exact family requires generation and fitted-hardware evidence",
      "key_variants": [
        {
          "type": "keyed",
          "status": "research_required"
        },
        {
          "type": "advanced_key_or_keyless",
          "status": "research_required"
        }
      ],
      "status": "research_in_progress",
      "verification_scope": "UK model history only."
    },
    {
      "id": "b6",
      "name": "A4 B6",
      "years": "2001-2005",
      "platform": "Audi longitudinal architecture; exact platform revision requires generation evidence",
      "immobiliser_family": "Exact family requires generation and fitted-hardware evidence",
      "key_variants": [
        {
          "type": "keyed",
          "status": "research_required"
        },
        {
          "type": "advanced_key_or_keyless",
          "status": "research_required"
        }
      ],
      "status": "research_in_progress",
      "verification_scope": "UK model history only."
    },
    {
      "id": "b7",
      "name": "A4 B7",
      "years": "2005-2008",
      "platform": "Audi longitudinal architecture; exact platform revision requires generation evidence",
      "immobiliser_family": "Exact family requires generation and fitted-hardware evidence",
      "key_variants": [
        {
          "type": "keyed",
          "status": "research_required"
        },
        {
          "type": "advanced_key_or_keyless",
          "status": "research_required"
        }
      ],
      "status": "research_in_progress",
      "verification_scope": "UK model history only."
    },
    {
      "id": "b8",
      "name": "A4 B8",
      "years": "2008-2015",
      "platform": "Audi longitudinal architecture; exact platform revision requires generation evidence",
      "immobiliser_family": "BCM2 / Immo V",
      "key_variants": [
        {
          "type": "keyed",
          "status": "research_required"
        },
        {
          "type": "advanced_key_or_keyless",
          "status": "research_required"
        }
      ],
      "status": "partially_verified",
      "verification_scope": "Abrites identifies this model/era within BCM2 coverage; exact vehicle hardware, UK specification and location remain unverified."
    },
    {
      "id": "b9",
      "name": "A4 B9",
      "years": "2015-2024",
      "platform": "Audi longitudinal architecture; exact platform revision requires generation evidence",
      "immobiliser_family": "Exact family requires generation and fitted-hardware evidence",
      "key_variants": [
        {
          "type": "keyed",
          "status": "research_required"
        },
        {
          "type": "advanced_key_or_keyless",
          "status": "research_required"
        }
      ],
      "status": "research_in_progress",
      "verification_scope": "UK model history only."
    }
  ],
  "sources": {
    "audi_uk_archive": {
      "publisher": "Audi UK Newsroom",
      "title": "UK current and previous model archive",
      "url": "https://press.audi.co.uk/models/concept/releases",
      "supports": [
        "UK model presence"
      ]
    },
    "abrites_vag_online": {
      "publisher": "Abrites",
      "title": "Diagnostics for VAG Online user manual",
      "url": "https://abrites.com/media/user_manuals/html/abrites-diagnostics-for-vag-online-user-manual/index.html",
      "supports": [
        "BCM2 application scope and operation constraints for named Audi models"
      ]
    }
  }
}
