[
  {
    "make": "Daihatsu",
    "model": "Sirion",
    "years": "1998-2004",
    "chip_type": "ID46",
    "frequency": "433",
    "im508s_compatible": "Yes - IM508S supports - OBD",
    "keydiy_kdx4_compatible": "Yes - B05-4",
    "can_do_obd": "Yes",
    "process_if_not_obd": "N/A",
    "bypass_cable": "No",
    "tools": [
      "Autel IM508S",
      "KEYDIY KD-X4"
    ]
  },
  {
    "make": "Daihatsu",
    "model": "Terios",
    "years": "1997-2005",
    "chip_type": "ID46",
    "frequency": "433",
    "im508s_compatible": "Yes - IM508S supports - OBD",
    "keydiy_kdx4_compatible": "Yes - B05-4",
    "can_do_obd": "Yes",
    "process_if_not_obd": "N/A",
    "bypass_cable": "No",
    "tools": [
      "Autel IM508S",
      "KEYDIY KD-X4"
    ]
  },
  {
    "make": "Daihatsu",
    "model": "Copen",
    "years": "2002-2012",
    "chip_type": "ID46",
    "frequency": "433",
    "im508s_compatible": "Yes - IM508S supports - OBD",
    "keydiy_kdx4_compatible": "Yes - B05-4",
    "can_do_obd": "Yes",
    "process_if_not_obd": "N/A",
    "bypass_cable": "No",
    "tools": [
      "Autel IM508S",
      "KEYDIY KD-X4"
    ]
  }
]