[
  {
    "make": "Genesis",
    "model": "G70",
    "years": "2017-2025",
    "chip_type": "ID47",
    "frequency": "433",
    "im508s_compatible": "Yes - IM508S supports - OBD, 2020+ 40-PIN + G-BOX3 IC chip",
    "keydiy_kdx4_compatible": "Yes - ZB04",
    "can_do_obd": "Yes",
    "process_if_not_obd": "N/A",
    "bypass_cable": "40-PIN for 2020+",
    "tools": [
      "Autel IM508S",
      "KEYDIY KD-X4"
    ]
  },
  {
    "make": "Genesis",
    "model": "G80",
    "years": "2016-2025",
    "chip_type": "ID47",
    "frequency": "433",
    "im508s_compatible": "Yes - IM508S supports - OBD, 2020+ 40-PIN + G-BOX3",
    "keydiy_kdx4_compatible": "Yes - ZB04",
    "can_do_obd": "Yes",
    "process_if_not_obd": "N/A",
    "bypass_cable": "40-PIN for 2020+",
    "tools": [
      "Autel IM508S",
      "KEYDIY KD-X4"
    ]
  },
  {
    "make": "Genesis",
    "model": "G90",
    "years": "2017-2025",
    "chip_type": "ID47",
    "frequency": "433",
    "im508s_compatible": "Yes - IM508S supports - OBD, 2020+ 40-PIN + G-BOX3",
    "keydiy_kdx4_compatible": "Yes - ZB04",
    "can_do_obd": "Yes",
    "process_if_not_obd": "N/A",
    "bypass_cable": "40-PIN for 2020+",
    "tools": [
      "Autel IM508S",
      "KEYDIY KD-X4"
    ]
  },
  {
    "make": "Genesis",
    "model": "GV70",
    "years": "2021-2025",
    "chip_type": "ID47",
    "frequency": "433",
    "im508s_compatible": "Yes - IM508S supports - OBD 40-PIN + G-BOX3",
    "keydiy_kdx4_compatible": "Yes - ZB04",
    "can_do_obd": "Yes",
    "process_if_not_obd": "N/A",
    "bypass_cable": "40-PIN",
    "tools": [
      "Autel IM508S",
      "KEYDIY KD-X4"
    ]
  },
  {
    "make": "Genesis",
    "model": "GV80",
    "years": "2020-2025",
    "chip_type": "ID47",
    "frequency": "433",
    "im508s_compatible": "Yes - IM508S supports - OBD 40-PIN + G-BOX3",
    "keydiy_kdx4_compatible": "Yes - ZB04",
    "can_do_obd": "Yes",
    "process_if_not_obd": "N/A",
    "bypass_cable": "40-PIN",
    "tools": [
      "Autel IM508S",
      "KEYDIY KD-X4"
    ]
  }
]