{
  "id": "VAG_MQB_IMMO5",
  "component_type": "immobiliser",
  "data": {
    "immobiliser": {
      "family": "MQB",
      "generation": "Gen4.5/5",
      "bcm": "BCM MQB",
      "gateway": "Gateway MQB",
      "kessy": "variant_dependent",
      "security_gateway": false,
      "sfd": false,
      "online_required": false,
      "pin_required": false,
      "cs_required": true,
      "mac_required": false
    }
  },
  "verification": {"status": "provisional", "confidence": "medium", "sources": []}
}
