{
  "schema_version": "1.1",
  "updated_at": "2026-07-23",
  "scope": "UK-market Volkswagen Group and related Bentley/Porsche model-family to immobiliser-system mapping",
  "mapping_status": "family_scope",
  "notes": [
    "These mappings connect each existing model family to the immobiliser systems it may use across its UK generations.",
    "The exact fitted system must be resolved by generation, build date, platform, cluster type and VIN before a workflow is recommended.",
    "A model-family link does not verify a programming procedure, tool, key, cable or AKL route.",
    "Bentley and Porsche are included where Volkswagen Group immobiliser or KESSY architecture is applicable; legacy or marque-specific systems remain unmapped until separately verified."
  ],
  "systems": {
    "vag_immo2": "IMMO 2",
    "vag_immo3": "IMMO 3",
    "vag_immo4": "IMMO 4",
    "vag_immo5": "IMMO 5",
    "vag_mqb48_mqb45": "MQB48 / MQB 4.5",
    "vag_mqb_5c": "MQB 5C",
    "vag_mqb_5d": "MQB 5D",
    "vag_kessy": "KESSY"
  },
  "manufacturers": {
    "volkswagen": {
      "name": "Volkswagen",
      "models": {
        "amarok": ["vag_immo4", "vag_immo5", "vag_kessy"],
        "arteon": ["vag_mqb48_mqb45", "vag_mqb_5c", "vag_kessy"],
        "beetle": ["vag_immo2", "vag_immo3", "vag_immo4", "vag_immo5"],
        "caddy": ["vag_immo3", "vag_immo4", "vag_mqb48_mqb45", "vag_mqb_5c"],
        "cc": ["vag_immo4", "vag_immo5", "vag_kessy"],
        "crafter": ["vag_immo4", "vag_immo5", "vag_mqb_5c", "vag_mqb_5d"],
        "eos": ["vag_immo4", "vag_immo5"],
        "golf": ["vag_immo2", "vag_immo3", "vag_immo4", "vag_immo5", "vag_mqb48_mqb45", "vag_mqb_5c", "vag_mqb_5d", "vag_kessy"],
        "id_3": ["vag_mqb_5d"],
        "id_4": ["vag_mqb_5d"],
        "id_5": ["vag_mqb_5d"],
        "id_buzz": ["vag_mqb_5d"],
        "jetta": ["vag_immo3", "vag_immo4", "vag_immo5", "vag_mqb48_mqb45"],
        "passat": ["vag_immo2", "vag_immo3", "vag_immo4", "vag_immo5", "vag_mqb48_mqb45", "vag_mqb_5c", "vag_kessy"],
        "polo": ["vag_immo2", "vag_immo3", "vag_immo4", "vag_immo5", "vag_mqb48_mqb45", "vag_mqb_5c"],
        "scirocco": ["vag_immo4", "vag_immo5"],
        "sharan": ["vag_immo3", "vag_immo4", "vag_immo5", "vag_kessy"],
        "t_cross": ["vag_mqb48_mqb45", "vag_mqb_5c"],
        "t_roc": ["vag_mqb48_mqb45", "vag_mqb_5c", "vag_kessy"],
        "taigo": ["vag_mqb_5c"],
        "tiguan": ["vag_immo4", "vag_immo5", "vag_mqb48_mqb45", "vag_mqb_5c", "vag_kessy"],
        "touareg": ["vag_immo3", "vag_immo4", "vag_immo5", "vag_kessy"],
        "touran": ["vag_immo3", "vag_immo4", "vag_immo5", "vag_mqb48_mqb45", "vag_mqb_5c"],
        "transporter": ["vag_immo3", "vag_immo4", "vag_immo5", "vag_mqb_5c", "vag_kessy"],
        "up": ["vag_immo4", "vag_immo5"]
      }
    },
    "audi": {
      "name": "Audi",
      "models": {
        "a1": ["vag_immo4", "vag_immo5", "vag_mqb48_mqb45", "vag_mqb_5c"],
        "a3": ["vag_immo2", "vag_immo3", "vag_immo4", "vag_immo5", "vag_mqb48_mqb45", "vag_mqb_5c", "vag_mqb_5d", "vag_kessy"],
        "q2": ["vag_mqb48_mqb45", "vag_mqb_5c", "vag_kessy"],
        "q3": ["vag_immo5", "vag_mqb48_mqb45", "vag_mqb_5c", "vag_kessy"],
        "tt": ["vag_immo3", "vag_immo4", "vag_immo5", "vag_mqb48_mqb45", "vag_mqb_5c", "vag_kessy"],
        "a4": ["vag_immo2", "vag_immo3", "vag_immo4", "vag_immo5", "vag_kessy"],
        "a5": ["vag_immo4", "vag_immo5", "vag_kessy"],
        "a6": ["vag_immo2", "vag_immo3", "vag_immo4", "vag_immo5", "vag_kessy"],
        "a7": ["vag_immo5", "vag_kessy"],
        "a8": ["vag_immo3", "vag_immo4", "vag_immo5", "vag_kessy"],
        "q5": ["vag_immo4", "vag_immo5", "vag_kessy"],
        "q7": ["vag_immo3", "vag_immo4", "vag_immo5", "vag_kessy"],
        "q8": ["vag_immo5", "vag_kessy"]
      }
    },
    "seat": {
      "name": "SEAT",
      "models": {
        "arona": ["vag_mqb48_mqb45", "vag_mqb_5c"],
        "ateca": ["vag_mqb48_mqb45", "vag_mqb_5c", "vag_kessy"],
        "ibiza": ["vag_immo2", "vag_immo3", "vag_immo4", "vag_immo5", "vag_mqb48_mqb45", "vag_mqb_5c"],
        "leon": ["vag_immo2", "vag_immo3", "vag_immo4", "vag_immo5", "vag_mqb48_mqb45", "vag_mqb_5c", "vag_mqb_5d", "vag_kessy"],
        "tarraco": ["vag_mqb48_mqb45", "vag_mqb_5c", "vag_kessy"],
        "toledo": ["vag_immo2", "vag_immo3", "vag_immo4", "vag_immo5"]
      }
    },
    "skoda": {
      "name": "Škoda",
      "models": {
        "fabia": ["vag_immo2", "vag_immo3", "vag_immo4", "vag_immo5", "vag_mqb48_mqb45", "vag_mqb_5c"],
        "karoq": ["vag_mqb48_mqb45", "vag_mqb_5c", "vag_kessy"],
        "kodiaq": ["vag_mqb48_mqb45", "vag_mqb_5c", "vag_kessy"],
        "octavia": ["vag_immo2", "vag_immo3", "vag_immo4", "vag_immo5", "vag_mqb48_mqb45", "vag_mqb_5c", "vag_mqb_5d", "vag_kessy"],
        "rapid": ["vag_immo4", "vag_immo5"],
        "superb": ["vag_immo3", "vag_immo4", "vag_immo5", "vag_mqb48_mqb45", "vag_mqb_5c", "vag_kessy"],
        "scala": ["vag_mqb48_mqb45", "vag_mqb_5c"]
      }
    },
    "bentley": {
      "name": "Bentley",
      "models": {
        "arnage": [],
        "bentayga": ["vag_immo5", "vag_kessy"],
        "continental": ["vag_immo4", "vag_immo5", "vag_kessy"],
        "flying_spur": ["vag_immo4", "vag_immo5", "vag_kessy"],
        "mulsanne": ["vag_kessy"]
      },
      "notes": {
        "arnage": "Legacy Bentley/Rolls-Royce-derived security architecture; do not inherit VAG workflow without separate verification.",
        "mulsanne": "KESSY association requires generation and fitted-hardware confirmation before workflow selection."
      }
    },
    "porsche": {
      "name": "Porsche",
      "models": {
        "718": ["vag_kessy"],
        "911": ["vag_kessy"],
        "924": [],
        "944": [],
        "968": [],
        "boxster": ["vag_kessy"],
        "cayenne": ["vag_immo3", "vag_immo4", "vag_immo5", "vag_kessy"],
        "cayman": ["vag_kessy"],
        "macan": ["vag_immo5", "vag_kessy"],
        "panamera": ["vag_immo5", "vag_kessy"],
        "taycan": ["vag_kessy"]
      },
      "notes": {
        "924": "Legacy Porsche system; outside the current VAG immobiliser families.",
        "944": "Legacy Porsche system; outside the current VAG immobiliser families.",
        "968": "Legacy Porsche system; outside the current VAG immobiliser families.",
        "718": "Marque-specific immobiliser implementation may sit behind KESSY/keyless functions; verify exact generation and module.",
        "911": "Spans many generations; do not infer one VAG workflow from the model-family link.",
        "boxster": "Spans multiple generations; exact immobiliser architecture must be resolved before workflow selection.",
        "cayman": "Spans multiple generations; exact immobiliser architecture must be resolved before workflow selection.",
        "taycan": "Later electronic architecture requires separate verified procedure data."
      }
    }
  },
  "resolution_requirements": [
    "Confirm exact model generation or chassis/platform",
    "Confirm build date and UK market application",
    "Confirm instrument-cluster or KESSY/BCM variant where relevant",
    "Confirm keyless/proximity equipment",
    "Use VIN or fitted hardware before selecting a programming workflow"
  ],
  "confidence": "research_required"
}