{
  "schema_version": "2.1",
  "model": "Celica",
  "market": "UK",
  "drive_side": "RHD",
  "generations": [
    {
      "id": "celica_uk_generations",
      "name": "Celica UK generations",
      "years": "1982-2006",
      "platform": "Generation-specific platform requires confirmation",
      "immobiliser_family": "Toyota immobiliser ECU/smart-entry family; generation specific",
      "key_variants": [
        {
          "type": "keyed",
          "status": "research_required"
        },
        {
          "type": "slot_key",
          "status": "research_required"
        },
        {
          "type": "proximity",
          "status": "research_required"
        },
        {
          "type": "KESSY_or_keyless",
          "status": "research_required"
        },
        {
          "type": "smart_key",
          "status": "research_required"
        }
      ],
      "status": "partially_verified"
    }
  ],
  "sources": {
    "official_range": {
      "publisher": "Toyota",
      "url": "https://www.toyota.co.uk/new-cars",
      "checked_at": "2026-07-18",
      "confidence": "high",
      "supports": [
        "UK model-family coverage"
      ]
    }
  }
}
